Metadata-Version: 1.1
Name: prettyrequire
Version: 1.0.0
Summary: Conditional control made pretty: require(condition, message) will raise an exception if condition is false.
Home-page: https://github.com/thecookingsenpai
Author: TheCookingSenpai
Author-email: drotosclerosi@gmail.com
License: BSD 2-clause
Platform: UNKNOWN
Classifier: Development Status :: 5 - Production/Stable
Classifier: Intended Audience :: Developers
